<?xml version="1.0" encoding="utf-8"?>
<entities>
    
    <!-- Load resources -->
    <resources>
        <resource kind="image">
            <image path="resources/img/map.png" alias="map"/>
        </resource>
        <resource kind="image">
            <image path="resources/img/cochon.png" alias="pig"/>
        </resource>
        <resource kind="image">
            <image path="resources/img/garcon_des_rues.png" alias="streetboy"/>
        </resource>
        <resource kind="image">
            <image path="resources/img/magicien.png" alias="wizard"/>
        </resource>
        <resource kind="image">
            <image path="resources/img/maire.png" alias="mayor"/>
        </resource>
        <resource kind="image">
            <image path="resources/img/princesse.png" alias="princess"/>
        </resource>
        <resource kind="image">
            <image path="resources/img/richard.png" alias="richard"/>
        </resource>
        <resource kind="image">
            <image path="resources/img/wall.png" alias="wall"/>
        </resource>
        
        <resource kind="font">
            <image path="resources/fonts/BerkshireSwash-Regular.ttf" alias="sans_big" size="30"/>
        </resource>
        <resource kind="font">
            <image path="resources/fonts/BerkshireSwash-Regular.ttf" alias="sans_small" size="8"/>
        </resource>
        
        <resource kind="sprite">
            <image path="sprites/walk_up" alias="man_walk_up"/>
        </resource>
        <resource kind="sprite">
            <image path="sprites/walk_left" alias="man_walk_left"/>
        </resource>
        <resource kind="sprite">
            <image path="sprites/walk_down" alias="man_walk_down"/>
        </resource>
        <resource kind="sprite">
            <image path="sprites/walk_right" alias="man_walk_right"/>
        </resource>
        <resource kind="sprite">
            <image path="sprites/stand_up" alias="man_stand_up"/>
        </resource>
        <resource kind="sprite">
            <image path="sprites/stand_left" alias="man_stand_left"/>
        </resource>
        <resource kind="sprite">
            <image path="sprites/stand_down" alias="man_stand_down"/>
        </resource>
        <resource kind="sprite">
            <image path="sprites/stand_right" alias="man_stand_right"/>
        </resource>
        <resource kind="sprite">
            <image path="sprites/wait" alias="man_still"/>
        </resource>
        <resource kind="sprite">
            <image path="sprites/gold_coin" alias="gold_coin"/>
        </resource>

        <resource kind="audio">
          <audio path="resources/music/Calmtown.ogg" alias="background_music" />
        </resource>
    </resources>
    
	<!-- create entity -->
    <entity>    
        <components>
            <component type="Resources" kind="image" gui="true" z-order="100">
                <image alias="wall"/>
            </component>
            <component type="Transform">
                <position x="600" y="0"/>
            </component>
            <component type="Controller" name="ButtonController" />
        </components>
    </entity>
        
    <!-- 
    <entity>
        <components>
            <component type="Resources" kind="image">
                <image alias="streetboy"/>
            </component>
            <component type="Transform">
                <position x="50" y="350"/>
            </component>
        </components>
    </entity>
        
    <entity>
        <components>
            <component type="Resources" kind="image">
                <image alias="mayor"/>
            </component>
            <component type="Transform">
                <position x="90" y="350"/>
            </component>
        </components>
    </entity>
        
    <entity>
        <components>
            <component type="Resources" kind="image">
                <image alias="princess"/>
            </component>
            <component type="Transform">
                <position x="130" y="350"/>
            </component>
        </components>
    </entity>
        
    <entity>
        <components>
            <component type="Resources" kind="image">
                <image alias="wizard"/>
            </component>
            <component type="Transform">
                <position x="170" y="350"/>
            </component>
        </components>
    </entity>
        
    <entity>
        <components>
            <component type="Resources" kind="image">
                <image alias="richard"/>
            </component>
            <component type="Transform">
                <position x="210" y="350"/>
            </component>
        </components>
    </entity>
    -->
    
	<entity>
		<!-- Tag list  -->
		<tags>
			<tag name="HERO" unique="true"></tag>
            <tag name="DummyTag" unique="false"></tag>
            <tag name="clever"></tag>
		</tags>
        <components>
            <component type="Transform">
                <position x="410" y="620"/>
            </component>
            <component type="Animated">
                <image name="man_stand_down"/>
            </component>
            <component type="Input">
            </component>
            <component type="Controller" name="HeroController" />
            <component type="Scriptable">
                <script name="toto"/>
            </component>
            <component type="Mobile">
            </component>
            <component type="Camera"
                       offsetX="100" offsetY="100"
                       width="600" height="600" />
            <component type="Character">
                <stats name="initiative" value="5"/>
                <stats name="health" value="50"/>
                <stats name="armor_class" value="3"/>
                <stats name="damage" value="1"/>
            </component>
        </components>
    </entity>

    <entity>
      <components>
        <component type="Transform"><position x="430" y="700"/></component>
        <component type="Animated"><image name="gold_coin" /></component>
      </components>
    </entity>
    
    <entity>
      <components>
        <component type="Resources" kind="audio">
          <audio alias="background_music" />
        </component>
      </components>
    </entity>
    
    <entity>
        <tags>
            <tag name="LABEL"></tag>
		</tags>
        <components>
            <component type="Transform">
                <position x="235" y="365"/>
            </component>
            <component type="Resources" kind="font" z-order="99">
                <text>Press [ESC] to quit...</text>
                <police name="sans_small"/>
            </component>
        </components>
    </entity>
    
    <entity>
        <tags>
            <tag name="LABEL"></tag>
		</tags>
        <components>
            <component type="Transform">
                <position x="290" y="475"/>
            </component>
            <component type="Resources" kind="font" z-order="99">
                <text>Chickenpix!</text>
                <police name="sans_big"/>
                <color r="255" g="255" b="0" a="128"/>
            </component>
        </components>
    </entity>
    
</entities>